CoDaBuddy/__init__.py
CoDaBuddy/backup_manager.py
CoDaBuddy/backupper.py
CoDaBuddy/cli.py
CoDaBuddy/cli_helper.py
CoDaBuddy/config.py
CoDaBuddy/container_helper.py
CoDaBuddy/executer.py
CoDaBuddy/label.py
CoDaBuddy/log.py
CoDaBuddy/main.py
CoDaBuddy-0.0.1.dist-info/LICENSE
CoDaBuddy-0.0.1.dist-info/METADATA
CoDaBuddy-0.0.1.dist-info/WHEEL
CoDaBuddy-0.0.1.dist-info/entry_points.txt
CoDaBuddy-0.0.1.dist-info/top_level.txt
CoDaBuddy-0.0.1.dist-info/RECORD
