Metadata-Version: 2.1
Name: CoDaBuddy
Version: 0.0.1
Summary: Container Database Backup - A tool to backup your database containers
Home-page: https://git.connect.dzd-ev.de/dzdtools/CoDaBuddy
Author: TB
Author-email: tim.bleimehl@helmholtz-muenchen.de
License: MIT
Platform: UNKNOWN
Requires-Python: >=3.7
License-File: LICENSE
Requires-Dist: DZDConfigs
Requires-Dist: Click
Requires-Dist: tabulate
Requires-Dist: humanize
Requires-Dist: pyyaml
